pm/vtt2txt/__about__.py
pm/vtt2txt/__init__.py
pm/vtt2txt/__main__.py
pm_vtt2txt-0.0.3.dist-info/METADATA
pm_vtt2txt-0.0.3.dist-info/WHEEL
pm_vtt2txt-0.0.3.dist-info/entry_points.txt
pm_vtt2txt-0.0.3.dist-info/licenses/LICENSE.txt
pm_vtt2txt-0.0.3.dist-info/RECORD
