Metadata-Version: 2.1
Name: pm-vtt2txt
Version: 0.0.3
Summary: Convert VTT file to plain text file
Project-URL: Documentation, https://github.com/TruthfulTechnology/pm-vtt2txt#readme
Project-URL: Issues, https://github.com/TruthfulTechnology/pm-vtt2txt/issues
Project-URL: Source, https://github.com/TruthfulTechnology/pm-vtt2txt
Author-email: Trey Hunner <trey@treyhunner.com>
License-Expression: MIT
License-File: LICENSE.txt
Classifier: Development Status :: 4 - Beta
Classifier: Programming Language :: Python
Classifier: Programming Language :: Python :: 3.7
Classifier: Programming Language :: Python :: 3.8
Classifier: Programming Language :: Python :: 3.9
Classifier: Programming Language :: Python :: 3.10
Classifier: Programming Language :: Python :: 3.11
Classifier: Programming Language :: Python :: Implementation :: CPython
Classifier: Programming Language :: Python :: Implementation :: PyPy
Requires-Python: >=3.7
